reasoner_pydantic/__init__.py
reasoner_pydantic/auxgraphs.py
reasoner_pydantic/base_model.py
reasoner_pydantic/kgraph.py
reasoner_pydantic/message.py
reasoner_pydantic/metakg.py
reasoner_pydantic/qgraph.py
reasoner_pydantic/results.py
reasoner_pydantic/shared.py
reasoner_pydantic/utils.py
reasoner_pydantic/workflow.py
reasoner_pydantic-6.0.0.dist-info/LICENSE
reasoner_pydantic-6.0.0.dist-info/METADATA
reasoner_pydantic-6.0.0.dist-info/WHEEL
reasoner_pydantic-6.0.0.dist-info/top_level.txt
reasoner_pydantic-6.0.0.dist-info/RECORD
