Metadata-Version: 2.1
Name: reasoner-pydantic
Version: 6.0.0
Summary: Pydantic models for the Reasoner API data formats
Home-page: https://github.com/TranslatorSRI/reasoner-pydantic
Author: Abrar Mesbah
Author-email: amesbah@covar.com
License: MIT
Requires-Python: >=3.9
License-File: LICENSE
Requires-Dist: pydantic<3,>=2
